{
  "lastUpdate": "2026-04-28",
  "article": {
    "title": "Agentes de IA Autonómos: Cómo Crear Empleados Virtuales que Trabajan 24/7 en Tu Empresa",
    "slug": "agentes-ia-autonomos-empleados-virtuales-empresas"
  },
  "calendarTasks": [
    {
      "date": "2024-12-20",
      "task": "Configurar AdSense y optimizar layout para anuncios",
      "agent": "Nacho",
      "priority": "alta"
    },
    {
      "date": "2024-12-21",
      "task": "Investigar y configurar primeros links de afiliados (herramientas IA)",
      "agent": "Nacho",
      "priority": "alta"
    },
    {
      "date": "2024-12-22",
      "task": "Crear landing page para newsletter y configurar lead magnets",
      "agent": "Nacho",
      "priority": "media"
    },
    {
      "date": "2024-12-23",
      "task": "Optimizar articulos top para mejor SEO y conversión",
      "agent": "Nacho",
      "priority": "media"
    },
    {
      "date": "2024-12-24",
      "task": "Configurar sistema de email marketing automatizado",
      "agent": "Nacho",
      "priority": "media"
    },
    {
      "date": "2024-12-26",
      "task": "Analizar métricas de diciembre y planear estrategia enero",
      "agent": "Nacho",
      "priority": "baja"
    }
  ],
  "integrationRequests": [
    {
      "agent": "Nacho",
      "service": "AdSense",
      "reason": "Con 155 artículos ya tenemos volumen para monetizar con anuncios display",
      "urgent": true
    },
    {
      "agent": "Nacho",
      "service": "Mailchimp",
      "reason": "Necesitamos capturar leads y hacer email marketing para aumentar retención",
      "urgent": true
    },
    {
      "agent": "Nacho",
      "service": "Amazon Associates",
      "reason": "Para comenzar con marketing de afiliados en herramientas IA recomendadas",
      "urgent": false
    }
  ],
  "weeklyNote": "El proyecto va sólido con 155 artículos y crecimiento orgánico. Es momento de monetizar: AdSense urgente, afiliados para enero, y captura de leads para construir audiencia propia."
}